ExplainAI/README.md
ExplainAI/__init__.py
ExplainAI/__pycache__/__init__.cpython-310.pyc
ExplainAI/example/__init__.py
ExplainAI/example/test.py
ExplainAI/example/__pycache__/__init__.cpython-310.pyc
ExplainAI/example/__pycache__/test.cpython-310.pyc
ExplainAI/explainers/__init__.py
ExplainAI/explainers/__pycache__/__init__.cpython-310.pyc
ExplainAI/explainers/__pycache__/__init__.cpython-36.pyc
ExplainAI/explainers/ale/__init__.py
ExplainAI/explainers/ale/ale.py
ExplainAI/explainers/ale/__pycache__/__init__.cpython-310.pyc
ExplainAI/explainers/ale/__pycache__/__init__.cpython-36.pyc
ExplainAI/explainers/ale/__pycache__/ale.cpython-310.pyc
ExplainAI/explainers/ale/__pycache__/ale.cpython-36.pyc
ExplainAI/explainers/ale/__pycache__/ale.cpython-37.pyc
ExplainAI/explainers/ice/__init__.py
ExplainAI/explainers/ice/ice.py
ExplainAI/explainers/ice/__pycache__/__init__.cpython-310.pyc
ExplainAI/explainers/ice/__pycache__/__init__.cpython-36.pyc
ExplainAI/explainers/ice/__pycache__/ice.cpython-310.pyc
ExplainAI/explainers/ice/__pycache__/ice.cpython-36.pyc
ExplainAI/explainers/ice/__pycache__/ice.cpython-37.pyc
ExplainAI/explainers/lime/__init__.py
ExplainAI/explainers/lime/lime_xai.py
ExplainAI/explainers/lime/__pycache__/__init__.cpython-310.pyc
ExplainAI/explainers/lime/__pycache__/__init__.cpython-36.pyc
ExplainAI/explainers/lime/__pycache__/lime_xai.cpython-310.pyc
ExplainAI/explainers/lime/__pycache__/lime_xai.cpython-36.pyc
ExplainAI/explainers/mfi/__init__.py
ExplainAI/explainers/mfi/mfi.py
ExplainAI/explainers/mfi/__pycache__/__init__.cpython-310.pyc
ExplainAI/explainers/mfi/__pycache__/__init__.cpython-36.pyc
ExplainAI/explainers/mfi/__pycache__/mfi.cpython-310.pyc
ExplainAI/explainers/mfi/__pycache__/mfi.cpython-36.pyc
ExplainAI/explainers/mfi/__pycache__/mfi.cpython-37.pyc
ExplainAI/explainers/pdp/__init__.py
ExplainAI/explainers/pdp/pdp.py
ExplainAI/explainers/pdp/pdp_calc_utils.py
ExplainAI/explainers/pdp/pdp_plot_utils.py
ExplainAI-0.2.9.dist-info/LICENSE
ExplainAI-0.2.9.dist-info/METADATA
ExplainAI-0.2.9.dist-info/WHEEL
ExplainAI-0.2.9.dist-info/top_level.txt
ExplainAI-0.2.9.dist-info/RECORD
