Metadata-Version: 2.1
Name: ExplainAI
Version: 0.2.9
Summary: explain AI tool
Home-page: https://github.com/HuangFeini/ExplainAI
Author: Feini Huang
Author-email: 386899557@qq.com
License: MIT Licence
Keywords: pip,ML,XAI,visualization
Platform: any
Classifier: Programming Language :: Python :: 3
Classifier: License :: OSI Approved :: MIT License
Classifier: Operating System :: OS Independent
Requires-Python: >=3.6
License-File: LICENSE
